aiacc_nccl/__init__.py
aiacc_nccl/libnccl.so.2
aiacc_nccl-2.17.1.dist-info/METADATA
aiacc_nccl-2.17.1.dist-info/WHEEL
aiacc_nccl-2.17.1.dist-info/top_level.txt
aiacc_nccl-2.17.1.dist-info/RECORD
